pytest_grpc/__init__.py
pytest_grpc/plugin.py
pytest_grpc-0.7.0.dist-info/METADATA
pytest_grpc-0.7.0.dist-info/WHEEL
pytest_grpc-0.7.0.dist-info/entry_points.txt
pytest_grpc-0.7.0.dist-info/top_level.txt
pytest_grpc-0.7.0.dist-info/RECORD
