Metadata-Version: 2.1
Name: pytest-grpc
Version: 0.7.0
Summary: pytest plugin for grpc
Home-page: UNKNOWN
Author: Denis Kataev
Author-email: denis.a.kataev@gmail.com
License: MIT
Platform: linux
Platform: osx
Platform: win32
Classifier: Framework :: Pytest
Classifier: Intended Audience :: Developers
Classifier: License :: OSI Approved :: MIT License
Classifier: Operating System :: POSIX
Classifier: Operating System :: Microsoft :: Windows
Classifier: Operating System :: MacOS :: MacOS X
Classifier: Topic :: Software Development :: Testing
Classifier: Topic :: Software Development :: Quality Assurance
Classifier: Topic :: Utilities
Classifier: Programming Language :: Python
Classifier: Programming Language :: Python :: 3.6
Classifier: Programming Language :: Python :: 3.7
Requires-Dist: pytest (>=3.6.0)
